[
  {
    "id": 1,
    "name": "Gaming Laptop",
    "category": "Electronics",
    "price": 999.99,
    "description": "A high-performance laptop perfect for gaming and work.",
    "image": "./assets/laptop-1.jpeg"
  },
  {
    "id": 2,
    "name": "Wireless Earbuds",
    "category": "Accessories",
    "price": 49.99,
    "description": "Bluetooth-enabled wireless earbuds with noise cancellation.",
    "image": "./assets/2.jpeg"
  },
  {
    "id": 3,
    "name": "Smart Watch",
    "category": "Wearables",
    "price": 199.99,
    "description": "Fitness tracking and notifications on your wrist.",
    "image": "./assets/3.jpeg"
  },
  {
    "id": 4,
    "name": "4K TV",
    "category": "Electronics",
    "price": 599.99,
    "description": "A 55-inch 4K Ultra HD TV with vibrant colors and smart features.",
    "image": "./assets/4.jpeg"
  },
  {
    "id": 5,
    "name": "Running Shoes",
    "category": "Sports",
    "price": 89.99,
    "description": "Lightweight and durable running shoes for everyday training.",
    "image": "./assets/5.jpeg"
  },
  {
    "id": 6,
    "name": "Bluetooth Speaker",
    "category": "Accessories",
    "price": 29.99,
    "description": "Portable Bluetooth speaker with rich sound and long battery life.",
    "image": "./assets/6.jpeg"
  },
  {
    "id": 7,
    "name": "Smartphone",
    "category": "Electronics",
    "price": 499.99,
    "description": "Latest model smartphone with high-resolution camera and fast performance.",
    "image": "./assets/7.jpeg"
  },
  {
    "id": 8,
    "name": "Backpack",
    "category": "Accessories",
    "price": 59.99,
    "description": "Stylish and durable backpack with multiple compartments.",
    "image": "./assets/8.jpeg"
  },
  {
    "id": 9,
    "name": "Coffee Maker",
    "category": "Home Appliances",
    "price": 39.99,
    "description": "Brew your favorite coffee with this compact coffee maker.",
    "image": "./assets/9.jpeg"
  },
  {
    "id": 10,
    "name": "Fitness Tracker",
    "category": "Wearables",
    "price": 129.99,
    "description": "Monitor your daily activity and heart rate with this fitness tracker.",
    "image": "./assets/10.jpeg"
  },
  {
    "id": 11,
    "name": "Electric Toothbrush",
    "category": "Health & Personal Care",
    "price": 79.99,
    "description": "Rechargeable electric toothbrush with multiple cleaning modes.",
    "image": "./assets/11.jpeg"
  },
  {
    "id": 12,
    "name": "Wireless Keyboard",
    "category": "Accessories",
    "price": 49.99,
    "description": "Slim wireless keyboard with comfortable typing and long battery life.",
    "image": "./assets/12.jpeg"
  },
  {
    "id": 13,
    "name": "Desk Lamp",
    "category": "Home Appliances",
    "price": 19.99,
    "description": "Adjustable desk lamp with LED lighting for optimal brightness.",
    "image": "./assets/13.png"
  },
  {
    "id": 14,
    "name": "Digital Camera",
    "category": "Electronics",
    "price": 299.99,
    "description": "Capture stunning photos and videos with this high-resolution digital camera.",
    "image": "./assets/14.jpeg"
  },
  {
    "id": 15,
    "name": "Yoga Mat",
    "category": "Sports",
    "price": 24.99,
    "description": "Non-slip yoga mat for all your exercise needs.",
    "image": "./assets/15.jpeg"
  },
  {
    "id": 16,
    "name": "Hair Dryer",
    "category": "Health & Personal Care",
    "price": 39.99,
    "description": "Fast-drying hair dryer with multiple heat settings.",
    "image": "./assets/16.jpeg"
  },
  {
    "id": 17,
    "name": "Blender",
    "category": "Home Appliances",
    "price": 59.99,
    "description": "High-power blender for smoothies and soups.",
    "image": "./assets/17.jpeg"
  },
  {
    "id": 18,
    "name": "Treadmill",
    "category": "Sports",
    "price": 799.99,
    "description": "High-performance treadmill with multiple incline settings.",
    "image": "./assets/18.jpeg"
  },
  {
    "id": 19,
    "name": "Noise Cancelling Headphones",
    "category": "Electronics",
    "price": 249.99,
    "description": "Over-ear headphones with active noise cancellation for immersive sound.",
    "image": "./assets/19.jpeg"
  },
  {
    "id": 20,
    "name": "Smart Thermostat",
    "category": "Home Appliances",
    "price": 149.99,
    "description": "Control your home temperature from anywhere with this smart thermostat.",
    "image": "./assets/20.jpeg"
  },
  {
    "id": 21,
    "name": "Gaming Mouse",
    "category": "Accessories",
    "price": 49.99,
    "description": "Ergonomic gaming mouse with adjustable DPI and RGB lighting.",
    "image": "./assets/21.jpeg"
  },
  {
    "id": 22,
    "name": "Camping Tent",
    "category": "Outdoor",
    "price": 199.99,
    "description": "Waterproof camping tent for 4 people, perfect for your next adventure.",
    "image": "./assets/22.jpeg"
  },
  {
    "id": 23,
    "name": "Electric Scooter",
    "category": "Electronics",
    "price": 399.99,
    "description": "Foldable electric scooter with a range of 20 miles on a single charge.",
    "image": "./assets/23.jpeg"
  },
  {
    "id": 24,
    "name": "Action Camera",
    "category": "Electronics",
    "price": 149.99,
    "description": "Waterproof action camera with 4K video recording capabilities.",
    "image": "./assets/24.jpeg"
  },
  {
    "id": 25,
    "name": "Air Fryer",
    "category": "Home Appliances",
    "price": 89.99,
    "description": "Healthier cooking with this air fryer, using minimal oil for crispy results.",
    "image": "./assets/25.jpeg"
  },
  {
    "id": 26,
    "name": "Laptop Stand",
    "category": "Accessories",
    "price": 29.99,
    "description": "Adjustable laptop stand for ergonomic comfort during long work hours.",
    "image": "./assets/26.jpeg"
  },
  {
    "id": 27,
    "name": "Portable Projector",
    "category": "Electronics",
    "price": 299.99,
    "description": "Compact projector for watching movies and presentations on the go.",
    "image": "./assets/27.jpeg"
  },

  {
    "id": 28,
    "name": "Water Bottle",
    "category": "Accessories",
    "price": 15.99,
    "description": "Durable stainless steel water bottle that keeps drinks cold or hot.",
    "image": "./assets/28.jpeg"
  },
  {
    "id": 29,
    "name": "Smart Light Switch",
    "category": "Home Automation",
    "price": 34.99,
    "description": "Control your lights from your smartphone with this smart light switch.",
    "image": "./assets/29.jpeg"
  },
  {
    "id": 30,
    "name": "Gaming Chair",
    "category": "Furniture",
    "price": 249.99,
    "description": "Comfortable gaming chair with adjustable features for long gaming sessions.",
    "image": "./assets/30.jpeg"
  },
  {
    "id": 31,
    "name": "Wireless Charging Pad",
    "category": "Accessories",
    "price": 19.99,
    "description": "Fast wireless charging pad compatible with most smartphones.",
    "image": "./assets/31.jpeg"
  },
  {
    "id": 32,
    "name": "Cookbook",
    "category": "Books",
    "price": 29.99,
    "description": "A collection of delicious recipes for home cooking.",
    "image": "./assets/32.jpeg"
  },
  {
    "id": 33,
    "name": "Travel Backpack",
    "category": "Accessories",
    "price": 89.99,
    "description": "Spacious travel backpack with multiple compartments and a padded laptop sleeve.",
    "image": "./assets/33.jpeg"
  },
  {
    "id": 34,
    "name": "Portable Bluetooth Speaker",
    "category": "Electronics",
    "price": 49.99,
    "description": "Compact Bluetooth speaker with excellent sound quality and long battery life.",
    "image": "./assets/34.jpeg"
  },
  {
    "id": 35,
    "name": "Electric Grill",
    "category": "Home Appliances",
    "price": 89.99,
    "description": "Indoor electric grill for grilling meats and vegetables.",
    "image": "./assets/35.jpeg"
  },
  {
    "id": 36,
    "name": "Pet Camera",
    "category": "Electronics",
    "price": 119.99,
    "description": "Monitor your pets remotely with this HD pet camera with two-way audio.",
    "image": "./assets/36.jpeg"
  },
  {
    "id": 37,
    "name": "VR Headset",
    "category": "Electronics",
    "price": 299.99,
    "description": "Virtual reality headset for an immersive gaming experience.",
    "image": "./assets/37.jpeg"
  },
  {
    "id": 38,
    "name": "Hiking Boots",
    "category": "Footwear",
    "price": 99.99,
    "description": "Durable and comfortable hiking boots for outdoor adventures.",
    "image": "./assets/38.jpeg"
  },
  {
    "id": 39,
    "name": "Wireless Router",
    "category": "Electronics",
    "price": 69.99,
    "description": "High-speed wireless router for seamless internet connectivity.",
    "image": "./assets/39.jpeg"
  },
  {
    "id": 40,
    "name": "Handheld Vacuum Cleaner",
    "category": "Home Appliances",
    "price": 39.99,
    "description": "Portable vacuum cleaner for quick clean-ups around the house.",
    "image": "./assets/40.jpeg"
  },
  {
    "id": 41,
    "name": "Smartphone Holder",
    "category": "Accessories",
    "price": 14.99,
    "description": "Adjustable smartphone holder for hands-free use.",
    "image": "./assets/41.jpeg"
  },
  {
    "id": 42,
    "name": "Yoga Block",
    "category": "Fitness",
    "price": 12.99,
    "description": "Supportive yoga block for improved flexibility and balance.",
    "image": "./assets/42.jpeg"
  },
  {
    "id": 43,
    "name": "Air Purifier",
    "category": "Home Appliances",
    "price": 129.99,
    "description": "HEPA air purifier for cleaner air and improved health.",
    "image": "./assets/43.jpeg"
  },
  {
    "id": 44,
    "name": "Instant Pot",
    "category": "Home Appliances",
    "price": 89.99,
    "description": "Multi-functional pressure cooker for quick and easy meal preparation.",
    "image": "./assets/44.jpeg"
  },
  {
    "id": 45,
    "name": "Digital Thermometer",
    "category": "Health & Personal Care",
    "price": 19.99,
    "description": "Accurate digital thermometer for quick temperature readings.",
    "image": "./assets/45.jpeg"
  },
  {
    "id": 46,
    "name": "Wireless Earphones",
    "category": "Accessories",
    "price": 59.99,
    "description": "Compact wireless earphones with touch controls and noise isolation.",
    "image": "./assets/46.jpeg"
  },
  {
    "id": 47,
    "name": "Camera Tripod",
    "category": "Photography",
    "price": 49.99,
    "description": "Sturdy tripod for stable photography and videography.",
    "image": "./assets/47.jpeg"
  },
  {
    "id": 48,
    "name": "Portable Grill",
    "category": "Outdoor",
    "price": 79.99,
    "description": "Compact portable grill perfect for camping and tailgating.",
    "image": "./assets/48.jpeg"
  },
  {
    "id": 49,
    "name": "Noise Cancelling Ear Muffs",
    "category": "Accessories",
    "price": 29.99,
    "description": "Protect your hearing with these comfortable noise-cancelling ear muffs.",
    "image": "./assets/49.jpeg"
  },
  {
    "id": 50,
    "name": "Electric Pressure Washer",
    "category": "Home Appliances",
    "price": 199.99,
    "description": "Powerful electric pressure washer for cleaning outdoor surfaces.",
    "image": "./assets/50.jpeg"
  },
  {
    "id": 51,
    "name": "Fitness Smartwatch",
    "category": "Wearables",
    "price": 179.99,
    "description": "Track your fitness goals with this feature-rich smartwatch.",
    "image": "./assets/51.jpeg"
  },
  {
    "id": 52,
    "name": "Electric Shaver",
    "category": "Health & Personal Care",
    "price": 59.99,
    "description": "Cordless electric shaver for a smooth and close shave.",
    "image": "./assets/52.jpeg"
  },
  {
    "id": 53,
    "name": "Portable Air Conditioner",
    "category": "Home Appliances",
    "price": 349.99,
    "description": "Energy-efficient portable air conditioner for cooling small spaces.",
    "image": "./assets/53.jpeg"
  },
  {
    "id": 54,
    "name": "Smart Home Hub",
    "category": "Home Automation",
    "price": 99.99,
    "description": "Control all your smart devices from one central hub.",
    "image": "./assets/54.jpeg"
  },
  {
    "id": 55,
    "name": "Electric Bike",
    "category": "Outdoor",
    "price": 799.99,
    "description": "Eco-friendly electric bike for convenient commuting.",
    "image": "./assets/55.jpeg"
  },
  {
    "id": 56,
    "name": "Multi-Tool Pocket Knife",
    "category": "Outdoor",
    "price": 24.99,
    "description": "Versatile pocket knife with multiple functions for outdoor enthusiasts.",
    "image": "./assets/56.jpeg"
  },
  {
    "id": 57,
    "name": "Wireless Security Camera",
    "category": "Home Security",
    "price": 89.99,
    "description": "Monitor your home with this easy-to-install wireless security camera.",
    "image": "./assets/57.jpeg"
  },
  {
    "id": 58,
    "name": "Digital Photo Frame",
    "category": "Electronics",
    "price": 79.99,
    "description": "Display your favorite photos with this digital photo frame.",
    "image": "./assets/58.jpeg"
  },
  {
    "id": 59,
    "name": "Cookware Set",
    "category": "Kitchen",
    "price": 129.99,
    "description": "Non-stick cookware set for hassle-free cooking.",
    "image": "./assets/59.jpeg"
  },{
    "id": 60,
    "name": "Vacuum Cleaner",
    "category": "Home Appliances",
    "price": 149.99,
    "description": "Powerful and lightweight vacuum cleaner for everyday cleaning.",
    "image": "./assets/60.jpeg"
  },
  {
    "id": 61,
    "name": "Robotic Vacuum",
    "category": "Home Appliances",
    "price": 249.99,
    "description": "Smart robotic vacuum cleaner that automatically cleans your floors.",
    "image": "./assets/61.jpeg"
  },
  {
    "id": 62,
    "name": "Electric Kettle",
    "category": "Kitchen",
    "price": 39.99,
    "description": "Fast boiling electric kettle with automatic shut-off.",
    "image": "./assets/62.jpeg"
  },
  {
    "id": 63,
    "name": "Bluetooth Speaker",
    "category": "Electronics",
    "price": 59.99,
    "description": "Portable Bluetooth speaker with high-quality sound.",
    "image": "./assets/63.jpeg"
  },
  {
    "id": 64,
    "name": "Portable Power Bank",
    "category": "Accessories",
    "price": 29.99,
    "description": "Charge your devices on the go with this compact power bank.",
    "image": "./assets/64.jpeg"
  },
  {
    "id": 65,
    "name": "Smart Doorbell",
    "category": "Home Security",
    "price": 149.99,
    "description": "Smart doorbell with video camera and two-way audio.",
    "image": "./assets/65.jpeg"
  },
  {
    "id": 66,
    "name": "Standing Desk",
    "category": "Office Furniture",
    "price": 299.99,
    "description": "Height-adjustable standing desk for a healthier workspace.",
    "image": "./assets/66.jpeg"
  },
  {
    "id": 67,
    "name": "Electric Toothbrush",
    "category": "Health & Personal Care",
    "price": 39.99,
    "description": "Rechargeable electric toothbrush with multiple cleaning modes.",
    "image": "./assets/67.jpeg"
  },
  {
    "id": 68,
    "name": "Smart Light Bulbs",
    "category": "Home Automation",
    "price": 49.99,
    "description": "Energy-efficient smart bulbs that you can control with your phone.",
    "image": "./assets/68.jpeg"
  },
  {
    "id": 69,
    "name": "Action Camera",
    "category": "Photography",
    "price": 199.99,
    "description": "Durable action camera for capturing high-quality video in extreme conditions.",
    "image": "./assets/69.jpeg"
  },
  {
    "id": 70,
    "name": "Electric Blanket",
    "category": "Bedding",
    "price": 79.99,
    "description": "Stay warm and cozy with this soft electric blanket.",
    "image": "./assets/70.jpeg"
  },
  {
    "id": 71,
    "name": "Smart Thermostat",
    "category": "Home Automation",
    "price": 199.99,
    "description": "Programmable smart thermostat for energy-efficient heating and cooling.",
    "image": "./assets/71.jpeg"
  },
  {
    "id": 72,
    "name": "Food Processor",
    "category": "Kitchen",
    "price": 99.99,
    "description": "Powerful food processor for chopping, slicing, and dicing.",
    "image": "./assets/72.jpeg"
  },
  {
    "id": 73,
    "name": "Gaming Chair",
    "category": "Office Furniture",
    "price": 199.99,
    "description": "Ergonomic gaming chair with lumbar support for comfort during long gaming sessions.",
    "image": "./assets/73.jpeg"
  },
  {
    "id": 74,
    "name": "Fitness Resistance Bands",
    "category": "Fitness",
    "price": 24.99,
    "description": "Set of resistance bands for strength training and flexibility exercises.",
    "image": "./assets/74.jpeg"
  },
  {
    "id": 75,
    "name": "Electric Hand Mixer",
    "category": "Kitchen",
    "price": 29.99,
    "description": "Compact electric hand mixer with multiple speed settings.",
    "image": "./assets/75.jpeg"
  },
  {
    "id": 76,
    "name": "Smartwatch Charging Dock",
    "category": "Accessories",
    "price": 19.99,
    "description": "Convenient charging dock for your smartwatch.",
    "image": "./assets/76.jpeg"
  },
  {
    "id": 77,
    "name": "Portable Camping Stove",
    "category": "Outdoor",
    "price": 59.99,
    "description": "Lightweight camping stove perfect for outdoor cooking.",
    "image": "./assets/77.jpeg"
  },
  {
    "id": 78,
    "name": "Adjustable Dumbbells",
    "category": "Fitness",
    "price": 149.99,
    "description": "Space-saving adjustable dumbbells for versatile strength training.",
    "image": "./assets/78.jpeg"
  },
  {
    "id": 79,
    "name": "Wireless Charging Pad",
    "category": "Accessories",
    "price": 29.99,
    "description": "Charge your phone wirelessly with this sleek charging pad.",
    "image": "./assets/79.jpeg"
  },
  {
    "id": 80,
    "name": "Inflatable Kayak",
    "category": "Outdoor",
    "price": 399.99,
    "description": "Durable inflatable kayak for enjoying lakes and rivers.",
    "image": "./assets/80.jpeg"
  },{
    "id": 81,
    "name": "Yoga Mat",
    "category": "Fitness",
    "price": 29.99,
    "description": "Non-slip yoga mat for comfort and stability during your workout.",
    "image": "./assets/81.jpeg"
  },
  {
    "id": 82,
    "name": "Smart Water Bottle",
    "category": "Fitness",
    "price": 49.99,
    "description": "Track your water intake with this smart water bottle that reminds you to stay hydrated.",
    "image": "./assets/82.jpeg"
  },
  {
    "id": 83,
    "name": "Air Fryer",
    "category": "Kitchen",
    "price": 129.99,
    "description": "Healthier cooking with this air fryer that uses less oil for crispy results.",
    "image": "./assets/83.jpeg"
  },
  {
    "id": 84,
    "name": "Cordless Hair Clipper",
    "category": "Health & Personal Care",
    "price": 39.99,
    "description": "Rechargeable cordless hair clipper for precise haircuts at home.",
    "image": "./assets/84.jpeg"
  },
  {
    "id": 85,
    "name": "Wireless Earbuds",
    "category": "Electronics",
    "price": 79.99,
    "description": "Comfortable wireless earbuds with noise cancellation and clear sound.",
    "image": "./assets/85.jpeg"
  },
  {
    "id": 86,
    "name": "Electric Pressure Cooker",
    "category": "Kitchen",
    "price": 99.99,
    "description": "Multi-functional electric pressure cooker for fast and easy meals.",
    "image": "./assets/86.jpeg"
  },
  {
    "id": 87,
    "name": "Bluetooth Headphones",
    "category": "Electronics",
    "price": 99.99,
    "description": "Over-ear Bluetooth headphones with rich bass and a long battery life.",
    "image": "./assets/87.jpeg"
  },
  {
    "id": 88,
    "name": "Portable Air Purifier",
    "category": "Home Appliances",
    "price": 79.99,
    "description": "Compact air purifier for cleaner air in small spaces.",
    "image": "./assets/88.jpeg"
  },
  {
    "id": 89,
    "name": "Men's Leather Jacket",
    "category": "Clothing",
    "price": 199.99,
    "description": "Stylish and durable leather jacket, perfect for casual and formal wear.",
    "image": "./assets/89.jpeg"
  },
  {
    "id": 90,
    "name": "Women's Summer Dress",
    "category": "Clothing",
    "price": 49.99,
    "description": "Lightweight and breezy summer dress for comfortable wear on warm days.",
    "image": "./assets/90.jpeg"
  },
  {
    "id": 91,
    "name": "Unisex Hoodie",
    "category": "Clothing",
    "price": 39.99,
    "description": "Comfortable and soft unisex hoodie, available in multiple colors.",
    "image": "./assets/91.jpeg"
  },
  {
    "id": 92,
    "name": "Men's Athletic Shorts",
    "category": "Clothing",
    "price": 29.99,
    "description": "Breathable and flexible athletic shorts for workouts and running.",
    "image": "./assets/92.jpeg"
  },
  {
    "id": 93,
    "name": "Women's Yoga Pants",
    "category": "Clothing",
    "price": 34.99,
    "description": "Stretchy and comfortable yoga pants designed for maximum movement.",
    "image": "./assets/93.jpeg"
  },
  {
    "id": 94,
    "name": "Men's Formal Suit",
    "category": "Clothing",
    "price": 299.99,
    "description": "Tailored formal suit, perfect for business meetings and special occasions.",
    "image": "./assets/94.jpeg"
  },
  {
    "id": 95,
    "name": "Women's Winter Coat",
    "category": "Clothing",
    "price": 129.99,
    "description": "Warm and fashionable winter coat with a faux fur-lined hood.",
    "image": "./assets/95.jpeg"
  },
  {
    "id": 96,
    "name": "Unisex Denim Jacket",
    "category": "Clothing",
    "price": 69.99,
    "description": "Classic denim jacket that pairs well with any outfit.",
    "image": "./assets/96.jpeg"
  },
  {
    "id": 97,
    "name": "Men's Graphic T-Shirt",
    "category": "Clothing",
    "price": 24.99,
    "description": "Casual graphic t-shirt with unique designs, available in various sizes.",
    "image": "./assets/97.jpeg"
  },
  {
    "id": 98,
    "name": "Women's High-Waisted Jeans",
    "category": "Clothing",
    "price": 59.99,
    "description": "High-waisted jeans with a slim fit for a flattering silhouette.",
    "image": "./assets/98.jpeg"
  },
  {
    "id": 99,
    "name": "Unisex Windbreaker Jacket",
    "category": "Clothing",
    "price": 49.99,
    "description": "Lightweight windbreaker jacket, perfect for outdoor activities.",
    "image": "./assets/99.jpeg"
  },
  {
    "id": 100,
    "name": "Men's Running Shoes",
    "category": "Clothing",
    "price": 89.99,
    "description": "Comfortable and durable running shoes for all terrains.",
    "image": "./assets/100.jpeg"
  }
  
]  
